bytedray_hive/__init__.py
bytedray_hive-0.0.1.dist-info/METADATA
bytedray_hive-0.0.1.dist-info/WHEEL
bytedray_hive-0.0.1.dist-info/top_level.txt
bytedray_hive-0.0.1.dist-info/RECORD
