Metadata-Version: 2.1
Name: bytedray-hive
Version: 0.0.1
Summary: A simple package named bytedray_hive
Home-page: https://github.com/artifact/bytedray_hive.git
Author: artifact
Author-email: artifact@example.com
License: UNKNOWN
Platform: UNKNOWN
Classifier: Programming Language :: Python :: 3
Classifier: License :: OSI Approved :: MIT License
Classifier: Operating System :: OS Independent
